[
    {
        "%vlocity_namespace%__ConditionData__c": "",
        "%vlocity_namespace%__DestinationDefaultQuantity__c": 1,
        "%vlocity_namespace%__DestinationMaxQuantity__c": 1,
        "%vlocity_namespace%__DestinationMinQuantity__c": 1,
        "%vlocity_namespace%__DestinationProductId__c": {
            "%vlocity_namespace%__GlobalKey__c": "c2a59fc9-24d3-cf47-d763-12df76a2bb1b",
            "VlocityDataPackType": "VlocityLookupMatchingKeyObject",
            "VlocityLookupRecordSourceKey": "Product2/c2a59fc9-24d3-cf47-d763-12df76a2bb1b",
            "VlocityRecordSObjectType": "Product2"
        },
        "%vlocity_namespace%__GlobalKey__c": "",
        "%vlocity_namespace%__MappingsData__c": "[{\"mapping_type\":\"ad-verbatim\",\"destination_attr_name\":\"MRC\",\"destination_attr_code\":\"ATTRIBUTE-121\",\"source_field_name\":\"Order.%vlocity_namespace%__EffectiveRecurringTotal__c\",\"source_type\":\"Field\"},{\"mapping_type\":\"ad-verbatim\",\"destination_attr_name\":\"NRC\",\"destination_attr_code\":\"ATTRIBUTE-122\",\"source_field_name\":\"Order.%vlocity_namespace%__EffectiveOneTimeTotal__c\",\"source_type\":\"Field\"},{\"mapping_type\":\"ad-verbatim\",\"destination_attr_name\":\"Billing Code\",\"destination_attr_code\":\"ATTRIBUTE-117\",\"source_field_name\":\"PricebookEntry.ProductCode\",\"source_type\":\"Field\"}]",
        "%vlocity_namespace%__Priority__c": "",
        "%vlocity_namespace%__RequireReservation__c": false,
        "%vlocity_namespace%__SourceDefaultQuantity__c": 1,
        "%vlocity_namespace%__SourceMaxQuantity__c": "",
        "%vlocity_namespace%__SourceMinQuantity__c": 1,
        "%vlocity_namespace%__SourceProductId__c": {
            "%vlocity_namespace%__GlobalKey__c": null,
            "VlocityDataPackType": "VlocityMatchingKeyObject",
            "VlocityMatchingRecordSourceKey": "VlocityRecordSourceKey:01t1N00000EUYeQQAX",
            "VlocityRecordSObjectType": "Product2"
        },
        "%vlocity_namespace%__XORGroup__c": "",
        "Name": "IP-VPN Billing Spec",
        "VlocityDataPackType": "SObject",
        "VlocityRecordSObjectType": "%vlocity_namespace%__DecompositionRelationship__c",
        "VlocityRecordSourceKey": "%vlocity_namespace%__DecompositionRelationship__c/IP-VPN Billing Spec/VlocityRecordSourceKey:01t1N00000EUYeQQAX"
    }
]